sundrip/__init__.py
sundrip/cli.py
sundrip/sundrip_config.yaml
sundrip/flask_app/NAMES.DIC
sundrip/flask_app/README.rst
sundrip/flask_app/config.py
sundrip/flask_app/run.py
sundrip/flask_app/testdata.py
sundrip/flask_app/__pycache__/config.cpython-310.pyc
sundrip/flask_app/__pycache__/config.cpython-39.pyc
sundrip/flask_app/__pycache__/run.cpython-310.pyc
sundrip/flask_app/__pycache__/testdata.cpython-310.pyc
sundrip/flask_app/app/__init__.py
sundrip/flask_app/app/index.py
sundrip/flask_app/app/models.py
sundrip/flask_app/app/security.py
sundrip/flask_app/app/views.py
sundrip/flask_app/app/__pycache__/__init__.cpython-310.pyc
sundrip/flask_app/app/__pycache__/__init__.cpython-39.pyc
sundrip/flask_app/app/__pycache__/index.cpython-310.pyc
sundrip/flask_app/app/__pycache__/index.cpython-39.pyc
sundrip/flask_app/app/__pycache__/models.cpython-310.pyc
sundrip/flask_app/app/__pycache__/models.cpython-39.pyc
sundrip/flask_app/app/__pycache__/security.cpython-310.pyc
sundrip/flask_app/app/__pycache__/security.cpython-39.pyc
sundrip/flask_app/app/__pycache__/views.cpython-310.pyc
sundrip/flask_app/app/__pycache__/views.cpython-39.pyc
sundrip/flask_app/app/templates/index.html
sundrip/flask_app/app/translations/pt/LC_MESSAGES/messages.mo
sundrip/flask_app/app/translations/pt/LC_MESSAGES/messages.po
sundrip/flask_app/babel/babel.cfg
sundrip/flask_app/babel/messages.pot
sundrip/flask_app/babel/messages.pot~
shihua_sundrip-0.1.1.dist-info/LICENSE
shihua_sundrip-0.1.1.dist-info/METADATA
shihua_sundrip-0.1.1.dist-info/WHEEL
shihua_sundrip-0.1.1.dist-info/entry_points.txt
shihua_sundrip-0.1.1.dist-info/top_level.txt
shihua_sundrip-0.1.1.dist-info/RECORD
