Metadata-Version: 2.1
Name: shihua-sundrip
Version: 0.1.1
Summary: Sundrip is the front-end of a production level algorithm engineering suite, which includes sunbskets (algorithm static management), sunflow (algorithm dynamic management), and sunshare (algorithm data interface).
Home-page: https://github.com/redblue0216/SunDrip
Author: shihua
Author-email: 15021408795@163.com
License: MIT
Requires-Python: >=3.10.9
License-File: LICENSE
